./.gitignore
./PKG-INFO
./README.md
./pyproject.toml
./strict_dataclasses.py
strict_dataclasses-0.1.0.dist-info/METADATA
strict_dataclasses-0.1.0.dist-info/WHEEL
strict_dataclasses-0.1.0.dist-info/RECORD
