Metadata-Version: 2.4
Name: strict-dataclasses
Version: 0.1.0
Summary: make dataclasses decorator type strict
Project-URL: Homepage, https://github.com/lxl66566/strict-dataclasses
Project-URL: Repository, https://github.com/lxl66566/strict-dataclasses.git
Project-URL: Documentation, https://github.com/lxl66566/strict-dataclasses
Author-email: lxl66566 <lxl66566@gmail.com>
License: MIT
Keywords: dataclass,strict typing,type checking,validation
Classifier: Programming Language :: Python :: 3
Classifier: Programming Language :: Python :: 3.11
Classifier: Programming Language :: Python :: 3.12
Classifier: Topic :: Software Development :: Libraries :: Python Modules
Classifier: Typing :: Typed
Requires-Python: >=3.11
